psrqpy/__init__.py
psrqpy/_version.py
psrqpy/config.py
psrqpy/pulsar.py
psrqpy/search.py
psrqpy/utils.py
psrqpy/tests/__init__.py
psrqpy/tests/conftest.py
psrqpy/tests/derived_catalogue.db
psrqpy/tests/query_test.py
psrqpy/tests/test_catalogue.db
psrqpy-1.3.2.dist-info/LICENSE
psrqpy-1.3.2.dist-info/METADATA
psrqpy-1.3.2.dist-info/WHEEL
psrqpy-1.3.2.dist-info/top_level.txt
psrqpy-1.3.2.dist-info/RECORD
