Metadata-Version: 2.2
Name: psrqpy
Version: 1.3.2
Summary: A Python module for querying the ATNF pulsar catalogue
Author-email: Matthew Pitkin <matthew.pitkin@ligo.org>
License: MIT
Project-URL: Source Code, https://github.com/mattpitkin/psrqpy
Project-URL: Documentation, https://psrqpy.readthedocs.io/
Classifier: Intended Audience :: Science/Research
Classifier: License :: OSI Approved :: MIT License
Classifier: Natural Language :: English
Classifier: Programming Language :: Python
Classifier: Programming Language :: Python :: 3
Classifier: Programming Language :: Python :: 3.8
Classifier: Programming Language :: Python :: 3.9
Classifier: Programming Language :: Python :: 3.10
Classifier: Topic :: Scientific/Engineering
Classifier: Topic :: Scientific/Engineering :: Astronomy
Requires-Python: <4,>=3.8
License-File: LICENSE
Requires-Dist: ads
Requires-Dist: appdirs
Requires-Dist: astropy>=3.2
Requires-Dist: beautifulsoup4
Requires-Dist: matplotlib
Requires-Dist: numpy>=1.16
Requires-Dist: packaging
Requires-Dist: pandas>0.21
Requires-Dist: requests
Requires-Dist: scipy
Provides-Extra: test
Requires-Dist: pytest>=3.9.1; extra == "test"
Requires-Dist: pytest-cov; extra == "test"
Requires-Dist: pytest-socket; extra == "test"
Provides-Extra: docs
Requires-Dist: autodoc; extra == "docs"
Requires-Dist: recommonmark; extra == "docs"
Requires-Dist: sphinx>=2.0; extra == "docs"
Requires-Dist: sphinx_rtd_theme; extra == "docs"
